MANIFEST.in
README
__init__.py
__pkginfo__.py
docparser.py
entities.py
hooks.py
schema.py
setup.py
site_cubicweb.py
sobjects.py
cubicweb_vcreview.egg-info/PKG-INFO
cubicweb_vcreview.egg-info/SOURCES.txt
cubicweb_vcreview.egg-info/dependency_links.txt
cubicweb_vcreview.egg-info/not-zip-safe
cubicweb_vcreview.egg-info/requires.txt
cubicweb_vcreview.egg-info/top_level.txt
data/cubes.vcreview.css
data/cubes.vcreview.js
data/warning_icon.png
i18n/en.po
i18n/fr.po
migration/0.1.1_Any.py
migration/0.1.2_Any.py
migration/0.1.3_Any.py
migration/0.2.0_Any.py
migration/0.4.0_Any.py
migration/0.4.1_Any.py
migration/0.4.2_Any.py
migration/0.5.0_Any.py
migration/0.6.1_Any.py
migration/0.7.0_Any.py
migration/0.8.0_Any.py
migration/0.8.1_Any.py
migration/0.8.2_Any.py
migration/0.9.1_Any.py
migration/postcreate.py
migration/precreate.py
test/test_vcreview.py
test/unittest_docparser.py
test/unittest_hooks.py
test/unittest_insertpoint.py
test/unittest_vcreview.py
views/__init__.py
views/components.py
views/facets.py
views/forms.py
views/primary.py
views/startup.py
wdoc/toc.xml
wdoc/vcreview_dailyuse_en.rst
wdoc/vcreview_en.rst
wdoc/vcreview_features_en.rst
wdoc/vcreview_setup_en.rst