Metadata-Version: 1.0
Name: cubicweb-vcreview
Version: 0.9.1
Summary: patch review system on top of vcsfile
Home-page: http://www.cubicweb.org/project/cubicweb-vcreview
Author: LOGILAB S.A. (Paris, FRANCE)
Author-email: contact@logilab.fr
License: LGPL
Platform: UNKNOWN
